lnrprog/__init__.py
lnrprog/lpp_graphical.py
lnrprog/two_phase_simplex.py
lnrprog-1.2.5.dist-info/LICENSE.txt
lnrprog-1.2.5.dist-info/METADATA
lnrprog-1.2.5.dist-info/WHEEL
lnrprog-1.2.5.dist-info/top_level.txt
lnrprog-1.2.5.dist-info/RECORD
