Metadata-Version: 2.1
Name: lnrprog
Version: 1.2.5
Summary: A project for solving linear programming problem
Home-page: https://github.com/Ashish2000L/linear_programing
Author: Ashish Kumar
Author-email: UNKNOWN
License: UNKNOWN
Platform: UNKNOWN
Requires-Dist: numpy (>=1.18.4)
Requires-Dist: matplotlib (>=3.2.1)
